np_ringbuffer/__init__.py
np_ringbuffer/ringbuffer.py
np_ringbuffer-1.0.0.dist-info/LICENSE
np_ringbuffer-1.0.0.dist-info/METADATA
np_ringbuffer-1.0.0.dist-info/WHEEL
np_ringbuffer-1.0.0.dist-info/top_level.txt
np_ringbuffer-1.0.0.dist-info/RECORD
