Metadata-Version: 2.1
Name: np_ringbuffer
Version: 1.0.0
Summary: A module for ring buffer operations using NumPy backend
Author: See Leung
Author-email: See Leung <sleung852@gmail.com>
License: MIT License
Project-URL: Home, https://github.com/sleung852/np_ringbuffer
Keywords: ringbuffer,timeseries,numpy
Classifier: License :: OSI Approved :: MIT License
Requires-Python: >=3.7
License-File: LICENSE
Requires-Dist: numpy
